odoo/addons/auth_signup_partner_company/README.rst
odoo/addons/auth_signup_partner_company/__init__.py
odoo/addons/auth_signup_partner_company/__manifest__.py
odoo/addons/auth_signup_partner_company/i18n/auth_signup_partner_company.pot
odoo/addons/auth_signup_partner_company/models/__init__.py
odoo/addons/auth_signup_partner_company/models/res_users.py
odoo/addons/auth_signup_partner_company/readme/DESCRIPTION.rst
odoo/addons/auth_signup_partner_company/static/description/icon.png
odoo/addons/auth_signup_partner_company/static/description/index.html
odoo/addons/auth_signup_partner_company/tests/__init__.py
odoo/addons/auth_signup_partner_company/tests/test_auth_signup_partner_company.py
odoo_addon_auth_signup_partner_company-15.0.1.0.0.7.dist-info/METADATA
odoo_addon_auth_signup_partner_company-15.0.1.0.0.7.dist-info/WHEEL
odoo_addon_auth_signup_partner_company-15.0.1.0.0.7.dist-info/top_level.txt
odoo_addon_auth_signup_partner_company-15.0.1.0.0.7.dist-info/RECORD
